LICENSE.txt
MANIFEST.in
README.md
pyproject.toml
setup.py
src/test_all.py
src/mercury_reels.egg-info/PKG-INFO
src/mercury_reels.egg-info/SOURCES.txt
src/mercury_reels.egg-info/dependency_links.txt
src/mercury_reels.egg-info/top_level.txt
src/reels/Clients.py
src/reels/Clips.py
src/reels/Events.py
src/reels/Intake.py
src/reels/Targets.py
src/reels/__init__.py
src/reels/create_tutorials.py
src/reels/imports.in
src/reels/main.dox
src/reels/py_reels.i
src/reels/py_reels_wrap.cpp
src/reels/reels.cpp
src/reels/reels.h
src/reels/reels_main.cpp
src/reels/reels_main.h
src/reels/reels_test.cpp
src/reels/reels_test.h
src/reels/thousand_sequences.hpp
src/reels/tutorials/reels_event_optimization.ipynb
src/reels/tutorials/reels_event_optimization_colab.ipynb
src/reels/tutorials/reels_walkthrough.ipynb
src/reels/tutorials/reels_walkthrough_colab.ipynb
src/reels/tutorials/data/reels_mansion.csv
src/reels/tutorials/data/reels_mansion_targets.csv
src/reels/tutorials/images/bounds_small.png
src/reels/tutorials/images/clients.png
src/reels/tutorials/images/clips.png
src/reels/tutorials/images/events.png
src/reels/tutorials/images/piece-puzzle.jpg
src/reels/tutorials/images/reels_classes.png
src/reels/tutorials/images/reels_logo.jpg
src/reels/tutorials/images/reels_small.png
src/reels/tutorials/images/targets.png